README.md
requirements.txt
botrun_drive_webhook/botrun_drive_webhook.py
botrun_drive_webhook/file_update_queue.py
botrun_drive_webhook/folder_path_cache.py
botrun_drive_webhook/google_file_webhook.py
botrun_drive_webhook-4.8.141.dist-info/METADATA
botrun_drive_webhook-4.8.141.dist-info/WHEEL
botrun_drive_webhook-4.8.141.dist-info/entry_points.txt
botrun_drive_webhook-4.8.141.dist-info/RECORD
