Metadata-Version: 2.3
Name: botrun_drive_webhook
Version: 4.8.141
Requires-Dist: backports-tarfile==1.2.0
Requires-Dist: build==1.2.1
Requires-Dist: cachetools==5.4.0
Requires-Dist: certifi==2024.7.4
Requires-Dist: charset-normalizer==3.3.2
Requires-Dist: docutils==0.21.2
Requires-Dist: google-api-core==2.19.1
Requires-Dist: google-api-python-client==2.138.0
Requires-Dist: google-auth-httplib2==0.2.0
Requires-Dist: google-auth==2.32.0
Requires-Dist: googleapis-common-protos==1.63.2
Requires-Dist: httplib2==0.22.0
Requires-Dist: idna==3.7
Requires-Dist: importlib-metadata==8.2.0
Requires-Dist: jaraco-classes==3.4.0
Requires-Dist: jaraco-context==5.3.0
Requires-Dist: jaraco-functools==4.0.2
Requires-Dist: jieba==0.42.1
Requires-Dist: keyring==25.3.0
Requires-Dist: markdown-it-py==3.0.0
Requires-Dist: mdurl==0.1.2
Requires-Dist: more-itertools==10.3.0
Requires-Dist: nh3==0.2.18
Requires-Dist: numpy==2.0.1
Requires-Dist: packaging==24.1
Requires-Dist: pandas==2.2.2
Requires-Dist: pkginfo==1.10.0
Requires-Dist: proto-plus==1.24.0
Requires-Dist: protobuf==5.27.2
Requires-Dist: pyasn1-modules==0.4.0
Requires-Dist: pyasn1==0.6.0
Requires-Dist: pygments==2.18.0
Requires-Dist: pyparsing==3.1.2
Requires-Dist: pyproject-hooks==1.1.0
Requires-Dist: python-dateutil==2.9.0.post0
Requires-Dist: python-dotenv==1.0.1
Requires-Dist: pytz==2024.1
Requires-Dist: readme-renderer==44.0
Requires-Dist: requests-toolbelt==1.0.0
Requires-Dist: requests==2.32.3
Requires-Dist: rfc3986==2.0.0
Requires-Dist: rich==13.7.1
Requires-Dist: rsa==4.9
Requires-Dist: six==1.16.0
Requires-Dist: twine==5.1.1
Requires-Dist: tzdata==2024.1
Requires-Dist: uritemplate==4.1.1
Requires-Dist: urllib3==2.2.2
Requires-Dist: zipp==3.19.2
